{
  "num_segments": 137,
  "total_area": 72363,
  "avg_area": 528.1970802919708,
  "avg_iou": 0.8950753847177881,
  "avg_stability": 0.9628669101826466,
  "largest_segments": [
    {
      "area": 64837,
      "bbox": [
        0,
        0,
        255,
        255
      ],
      "iou": 0.9937378764152527,
      "stability": 0.929949939250946
    },
    {
      "area": 472,
      "bbox": [
        236,
        55,
        19,
        37
      ],
      "iou": 0.9259531497955322,
      "stability": 0.956250011920929
    },
    {
      "area": 230,
      "bbox": [
        76,
        198,
        16,
        16
      ],
      "iou": 0.8605469465255737,
      "stability": 0.9618644118309021
    },
    {
      "area": 196,
      "bbox": [
        57,
        27,
        14,
        15
      ],
      "iou": 0.9320523142814636,
      "stability": 0.9306930899620056
    },
    {
      "area": 163,
      "bbox": [
        240,
        213,
        15,
        11
      ],
      "iou": 0.8867641091346741,
      "stability": 0.9585798978805542
    },
    {
      "area": 156,
      "bbox": [
        159,
        146,
        8,
        20
      ],
      "iou": 0.9033836722373962,
      "stability": 0.9447852969169617
    },
    {
      "area": 154,
      "bbox": [
        108,
        132,
        13,
        13
      ],
      "iou": 0.878442645072937,
      "stability": 0.9496855139732361
    },
    {
      "area": 145,
      "bbox": [
        179,
        128,
        10,
        15
      ],
      "iou": 0.8860151767730713,
      "stability": 0.9463087320327759
    },
    {
      "area": 141,
      "bbox": [
        58,
        30,
        11,
        12
      ],
      "iou": 0.8793215155601501,
      "stability": 0.9724137783050537
    },
    {
      "area": 130,
      "bbox": [
        39,
        248,
        19,
        7
      ],
      "iou": 0.8726784586906433,
      "stability": 0.9769230484962463
    }
  ]
}