{
  "num_segments": 43,
  "total_area": 67656,
  "avg_area": 1573.3953488372092,
  "avg_iou": 0.8995243518851525,
  "avg_stability": 0.9635724009469498,
  "largest_segments": [
    {
      "area": 65426,
      "bbox": [
        0,
        0,
        255,
        255
      ],
      "iou": 1.0070123672485352,
      "stability": 0.9625396728515625
    },
    {
      "area": 563,
      "bbox": [
        244,
        188,
        11,
        67
      ],
      "iou": 0.8630738258361816,
      "stability": 0.9208261370658875
    },
    {
      "area": 126,
      "bbox": [
        187,
        243,
        10,
        12
      ],
      "iou": 0.9052705764770508,
      "stability": 0.961240291595459
    },
    {
      "area": 118,
      "bbox": [
        232,
        139,
        8,
        19
      ],
      "iou": 0.8849630355834961,
      "stability": 0.925000011920929
    },
    {
      "area": 95,
      "bbox": [
        241,
        138,
        7,
        13
      ],
      "iou": 0.9154560565948486,
      "stability": 0.969072163105011
    },
    {
      "area": 87,
      "bbox": [
        152,
        59,
        8,
        12
      ],
      "iou": 0.8904068470001221,
      "stability": 0.977011501789093
    },
    {
      "area": 65,
      "bbox": [
        186,
        166,
        8,
        8
      ],
      "iou": 0.9257110357284546,
      "stability": 0.9285714030265808
    },
    {
      "area": 63,
      "bbox": [
        190,
        206,
        10,
        6
      ],
      "iou": 0.9032590389251709,
      "stability": 0.9682539701461792
    },
    {
      "area": 62,
      "bbox": [
        245,
        94,
        6,
        10
      ],
      "iou": 0.899340033531189,
      "stability": 0.9516128897666931
    },
    {
      "area": 60,
      "bbox": [
        79,
        186,
        9,
        6
      ],
      "iou": 0.8676974773406982,
      "stability": 0.9516128897666931
    }
  ]
}